tg_loger/__init__.py
tg_loger/tg.py
tg_loger-0.1.2.dist-info/METADATA
tg_loger-0.1.2.dist-info/WHEEL
tg_loger-0.1.2.dist-info/top_level.txt
tg_loger-0.1.2.dist-info/RECORD
